README.md
setup.py
pocket_stats/__init__.py
pocket_stats/__main__.py
pocket_stats/app.py
pocket_stats/constants.py
pocket_stats/data.py
pocket_stats/visualization.py
pocket_stats.egg-info/PKG-INFO
pocket_stats.egg-info/SOURCES.txt
pocket_stats.egg-info/dependency_links.txt
pocket_stats.egg-info/not-zip-safe
pocket_stats.egg-info/requires.txt
pocket_stats.egg-info/top_level.txt