Metadata-Version: 2.1
Name: pocket-stats
Version: 0.3.1
Summary: Tools for the Pocket reading app https://app.getpocket.com/
Home-page: https://github.com/nlbao/pocket_stats.git
Author: Bao Nguyen
Author-email: nlbao95@gmail.com
License: MIT
Platform: UNKNOWN
